ariadne_jwt/__init__.py
ariadne_jwt/__version__.py
ariadne_jwt/backends.py
ariadne_jwt/decorators.py
ariadne_jwt/exceptions.py
ariadne_jwt/middleware.py
ariadne_jwt/mutations.py
ariadne_jwt/scalar.py
ariadne_jwt/settings.py
ariadne_jwt/shortcuts.py
ariadne_jwt/testcases.py
ariadne_jwt/utils.py
ariadne_jwt/refresh_token/__init__.py
ariadne_jwt/refresh_token/apps.py
ariadne_jwt/refresh_token/managers.py
ariadne_jwt/refresh_token/models.py
ariadne_jwt/refresh_token/mutations.py
ariadne_jwt/refresh_token/shortcuts.py
ariadne_jwt/refresh_token/signals.py
ariadne_jwt/refresh_token/admin/__init__.py
ariadne_jwt/refresh_token/admin/filters.py
ariadne_jwt/refresh_token/management/__init__.py
ariadne_jwt/refresh_token/management/commands/__init__.py
ariadne_jwt/refresh_token/management/commands/cleartokens.py
ariadne_jwt/refresh_token/migrations/0001_initial.py
ariadne_jwt/refresh_token/migrations/__init__.py
ariadne_jwt-0.1.7.dist-info/LICENSE
ariadne_jwt-0.1.7.dist-info/METADATA
ariadne_jwt-0.1.7.dist-info/WHEEL
ariadne_jwt-0.1.7.dist-info/top_level.txt
ariadne_jwt-0.1.7.dist-info/RECORD
