Metadata-Version: 2.1
Name: ariadne-jwt
Version: 0.1.7
Summary: JSON Web Token for Ariadne Django
Home-page: https://github.com/Usama0121/ariadne-jwt
Author: Muhammad Usama
Author-email: aslam0121@gmail.com
License: MIT
Platform: UNKNOWN
Classifier: License :: OSI Approved :: MIT License
Classifier: Environment :: Web Environment
Classifier: Operating System :: OS Independent
Classifier: Intended Audience :: Developers
Classifier: Programming Language :: Python
Classifier: Programming Language :: Python :: 3
Classifier: Programming Language :: Python :: 3.6
Classifier: Programming Language :: Python :: 3.7
Classifier: Framework :: Django
Requires-Python: >=3.6.0
Requires-Dist: ariadne (>=0.12.0)
Requires-Dist: Django (>=2.2)
Requires-Dist: PyJWT (<3.0.0,>=1.7.1)
Requires-Dist: promise (==2.3)
